<mxGraphModel dx="1626" dy="3138" grid="1" guides="1" tooltips="1" connect="1" fold="1" page="0" pageScale="1" pageWidth="826" pageHeight="1169" style="default-style2"><root><mxCell id="0"/><mxCell id="1" parent="0"/><mxCell id="9" value="*&#xa;REPOSITORY" style="rounded=1" parent="1" vertex="1"><mxGeometry x="-15" y="-1223" width="830" height="110" as="geometry"/></mxCell><mxCell id="21" value="" style="edgeStyle=none" parent="1" source="20" target="9" edge="1"><mxGeometry x="435" y="-1104" width="100" height="100" as="geometry"><mxPoint x="745" y="-1044" as="sourcePoint"/><mxPoint x="535" y="-1104" as="targetPoint"/></mxGeometry></mxCell><mxCell id="22" value="Object-Relational Mapping Layer" style="swimlane;horizontal=0;startSize=32" parent="1" vertex="1"><mxGeometry x="125" y="-954" width="540" height="240" as="geometry"/></mxCell><mxCell id="25" value="OBJECT_DISASSEMBLER" style="rounded=1" parent="22" vertex="1"><mxGeometry x="250" y="30" width="170" height="60" as="geometry"/></mxCell><mxCell id="26" value="WRITE_PLANNER" style="rounded=1" parent="22" vertex="1"><mxGeometry x="377.5" y="100" width="150" height="40" as="geometry"/></mxCell><mxCell id="23" value="RETRIEVAL_MANAGER" style="rounded=1" parent="22" vertex="1"><mxGeometry x="40" y="45" width="145" height="150" as="geometry"/></mxCell><mxCell id="54" value="*&#xa;COLLECTION_HANDLER" style="rounded=1" vertex="1" parent="22"><mxGeometry x="240" y="160" width="155" height="60" as="geometry"/></mxCell><mxCell id="55" value="" style="arrow;edgeStyle=segmentEdgeStyle" edge="1" parent="22" source="23" target="54"><mxGeometry x="260" y="90" width="100" height="100" as="geometry"><mxPoint x="260" y="190" as="sourcePoint"/><mxPoint x="360" y="90" as="targetPoint"/><Array as="points"><mxPoint x="270" y="100"/></Array></mxGeometry></mxCell><mxCell id="56" value="" style="arrow;edgeStyle=segmentEdgeStyle" edge="1" parent="22" source="25" target="54"><mxGeometry x="140" y="-50" width="100" height="100" as="geometry"><mxPoint x="140" y="50" as="sourcePoint"/><mxPoint x="240" y="-50" as="targetPoint"/></mxGeometry></mxCell><mxCell id="31" value="*&#xa;BACKEND_STRATEGY" style="rounded=1" parent="1" vertex="1"><mxGeometry x="55" y="-624" width="610" height="60" as="geometry"/></mxCell><mxCell id="32" value="" style="arrow" parent="1" source="23" target="31" edge="1"><mxGeometry x="385" y="-684" width="100" height="100" as="geometry"><mxPoint x="385" y="-584" as="sourcePoint"/><mxPoint x="485" y="-684" as="targetPoint"/></mxGeometry></mxCell><mxCell id="33" value="" style="arrow" parent="1" source="27" target="31" edge="1"><mxGeometry x="375" y="-754" width="100" height="100" as="geometry"><mxPoint x="375" y="-654" as="sourcePoint"/><mxPoint x="475" y="-754" as="targetPoint"/></mxGeometry></mxCell><mxCell id="35" value="" style="line" parent="1" vertex="1"><mxGeometry x="-95" y="-1204" width="980" height="10" as="geometry"/></mxCell><mxCell id="36" value="Frontend" style="text" parent="1" vertex="1"><mxGeometry x="-85" y="-1230" width="100" height="26" as="geometry"/></mxCell><mxCell id="37" value="Backend" style="text" parent="1" vertex="1"><mxGeometry x="-85" y="-1199" width="40" height="26" as="geometry"/></mxCell><mxCell id="42" value="+&#xa;IN_MEMORY_DATABASE" style="rounded=1" parent="1" vertex="1"><mxGeometry x="-55" y="-514" width="170" height="60" as="geometry"/></mxCell><mxCell id="43" value="" style="edgeStyle=none" parent="1" target="31" edge="1" source="42"><mxGeometry x="565" y="-554" width="100" height="100" as="geometry"><mxPoint x="635" y="-484" as="sourcePoint"/><mxPoint x="665" y="-554" as="targetPoint"/></mxGeometry></mxCell><mxCell id="44" value="+&#xa;GENERIC_LAYOUT_SQL_BACKEND" style="rounded=1" parent="1" vertex="1"><mxGeometry x="275" y="-524" width="260" height="60" as="geometry"/></mxCell><mxCell id="45" value="" style="edgeStyle=none" parent="1" source="44" target="31" edge="1"><mxGeometry x="145" y="-654" width="100" height="100" as="geometry"><mxPoint x="145" y="-554" as="sourcePoint"/><mxPoint x="245" y="-654" as="targetPoint"/></mxGeometry></mxCell><mxCell id="27" value="WRITE_EXECUTOR" style="rounded=1" parent="1" vertex="1"><mxGeometry x="425" y="-704" width="355" height="40" as="geometry"/></mxCell><mxCell id="30" value="" style="arrow;edgeStyle=segmentEdgeStyle" parent="1" source="26" target="27" edge="1"><mxGeometry x="105" y="-794" width="100" height="100" as="geometry"><mxPoint x="105" y="-694" as="sourcePoint"/><mxPoint x="205" y="-794" as="targetPoint"/></mxGeometry></mxCell><mxCell id="20" value="+&#xa;RELATIONAL_REPOSITORY" style="rounded=1" parent="1" vertex="1"><mxGeometry x="335" y="-1084" width="460" height="60" as="geometry"/></mxCell><mxCell id="28" value="" style="arrow" parent="1" source="20" target="25" edge="1"><mxGeometry x="195" y="-984" width="100" height="100" as="geometry"><mxPoint x="195" y="-884" as="sourcePoint"/><mxPoint x="365" y="-944" as="targetPoint"/></mxGeometry></mxCell><mxCell id="29" value="" style="arrow;edgeStyle=segmentEdgeStyle" parent="1" source="20" target="26" edge="1"><mxGeometry x="160" y="-934" width="100" height="100" as="geometry"><mxPoint x="210" y="-984" as="sourcePoint"/><mxPoint x="318" y="-864" as="targetPoint"/><Array as="points"/></mxGeometry></mxCell><mxCell id="24" value="" style="arrow" parent="1" source="20" target="23" edge="1"><mxGeometry x="-245" y="-994" width="100" height="100" as="geometry"><mxPoint x="-245" y="-894" as="sourcePoint"/><mxPoint x="-145" y="-994" as="targetPoint"/></mxGeometry></mxCell><mxCell id="58" value="METADATA_TABLES_MANAGER&#xa;" style="rounded=1" vertex="1" parent="1"><mxGeometry x="630" y="-484" width="210" height="50" as="geometry"/></mxCell><mxCell id="59" value="SQL_DATABASE_ABSTRACTION" style="rounded=1" vertex="1" parent="1"><mxGeometry x="220" y="-404" width="235" height="60" as="geometry"/></mxCell><mxCell id="60" value="SQL_CONNECTION_ABSTRACTION" style="rounded=1" vertex="1" parent="1"><mxGeometry x="545" y="-334" width="270" height="60" as="geometry"/></mxCell><mxCell id="62" value="" style="arrow;exitX=1;exitY=0.75" edge="1" parent="1" source="44" target="58"><mxGeometry x="525" y="-474" width="100" height="100" as="geometry"><mxPoint x="525" y="-374" as="sourcePoint"/><mxPoint x="625" y="-474" as="targetPoint"/></mxGeometry></mxCell><mxCell id="63" value="" style="arrow" edge="1" parent="1" source="44" target="59"><mxGeometry x="405" y="-354" width="100" height="100" as="geometry"><mxPoint x="405" y="-254" as="sourcePoint"/><mxPoint x="505" y="-354" as="targetPoint"/></mxGeometry></mxCell><mxCell id="64" value="" style="arrow" edge="1" parent="1" source="59" target="60"><mxGeometry x="445" y="-294" width="100" height="100" as="geometry"><mxPoint x="445" y="-194" as="sourcePoint"/><mxPoint x="545" y="-294" as="targetPoint"/></mxGeometry></mxCell><mxCell id="65" value="" style="arrow" edge="1" parent="1" source="58" target="60"><mxGeometry x="695" y="-394" width="100" height="100" as="geometry"><mxPoint x="695" y="-294" as="sourcePoint"/><mxPoint x="795" y="-394" as="targetPoint"/></mxGeometry></mxCell><mxCell id="67" value="IN_MEMORY_REPOSITORY" style="rounded=1" vertex="1" parent="1"><mxGeometry x="-55" y="-1044" width="170" height="70" as="geometry"/></mxCell><mxCell id="68" value="" style="arrow" edge="1" parent="1" source="67" target="42"><mxGeometry x="-35" y="-864" width="100" height="100" as="geometry"><mxPoint x="-35" y="-764" as="sourcePoint"/><mxPoint x="65" y="-864" as="targetPoint"/></mxGeometry></mxCell><mxCell id="69" value="" style="edgeStyle=none" edge="1" parent="1" source="67" target="20"><mxGeometry x="105" y="-1054" width="100" height="100" as="geometry"><mxPoint x="105" y="-954" as="sourcePoint"/><mxPoint x="205" y="-1054" as="targetPoint"/></mxGeometry></mxCell><mxCell id="71" value="OBJECT_&#xa;IDENTIFICATION_&#xa;MANAGER" style="rounded=1" vertex="1" parent="1"><mxGeometry x="725" y="-949" width="130" height="190" as="geometry"/></mxCell><mxCell id="72" value="" style="arrow" edge="1" parent="1" source="20" target="71"><mxGeometry x="685" y="-1004" width="100" height="100" as="geometry"><mxPoint x="685" y="-904" as="sourcePoint"/><mxPoint x="785" y="-1004" as="targetPoint"/></mxGeometry></mxCell><mxCell id="73" value="" style="arrow" edge="1" parent="1" source="27" target="71"><mxGeometry x="725" y="-734" width="100" height="100" as="geometry"><mxPoint x="725" y="-634" as="sourcePoint"/><mxPoint x="825" y="-734" as="targetPoint"/></mxGeometry></mxCell><mxCell id="74" value="KEY_POID_TABLE" style="rounded=1" vertex="1" parent="1"><mxGeometry x="735" y="-604" width="120" height="60" as="geometry"/></mxCell><mxCell id="75" value="" style="arrow" edge="1" parent="1" source="31" target="74"><mxGeometry x="675" y="-574" width="100" height="100" as="geometry"><mxPoint x="675" y="-474" as="sourcePoint"/><mxPoint x="775" y="-574" as="targetPoint"/></mxGeometry></mxCell></root></mxGraphModel>